ckatorch/__init__.py
ckatorch/cka.py
ckatorch/core.py
ckatorch/hsic.py
ckatorch/plot.py
ckatorch/utils.py
ckatorch-1.0.2.dist-info/METADATA
ckatorch-1.0.2.dist-info/WHEEL
ckatorch-1.0.2.dist-info/licenses/LICENSE
ckatorch-1.0.2.dist-info/RECORD
