Metadata-Version: 2.4
Name: ckatorch
Version: 1.0.2
Summary: Centered Kernel Alignment in PyTorch
Project-URL: Homepage, https://github.com/RistoAle97/centered-kernel-alignment
Project-URL: Repository, https://github.com/RistoAle97/centered-kernel-alignment
Project-URL: Issues, https://github.com/RistoAle97/centered-kernel-alignment/issues
Author-email: Alessandro Ristori <aleristori97@gmail.com>
License: MIT License
License-File: LICENSE
Keywords: CKA,Centered Kernel Alignment,Deep Learning,Neural Network Similarity
Classifier: Development Status :: 5 - Production/Stable
Classifier: Intended Audience :: Science/Research
Classifier: License :: OSI Approved :: MIT License
Classifier: Programming Language :: Python :: 3 :: Only
Classifier: Programming Language :: Python :: 3.10
Classifier: Programming Language :: Python :: 3.11
Classifier: Programming Language :: Python :: 3.12
Classifier: Programming Language :: Python :: 3.13
Classifier: Topic :: Scientific/Engineering :: Artificial Intelligence
Requires-Python: >=3.10
Requires-Dist: matplotlib>=3.8.0
Requires-Dist: pyyaml>=6.0.2
Requires-Dist: safetensors>=0.4.2
Requires-Dist: seaborn>=0.12.2
Requires-Dist: torch>=2.3.1
Requires-Dist: tqdm>=4.66.3
